{"is_source_file": true, "format": "JavaScript/JSX", "description": "React component 'Favorites' rendering a list of favorite recipes, using memoization for efficiency.", "external_files": ["../components/RecipeCard"], "external_methods": ["React", "useMemo"], "published": [], "classes": [], "methods": [{"name": "Favorites({ recipes, favorites, openRecipe, toggleFavorite })", "description": "React functional component displaying user's favorite recipes, filtered from a list based on favorite IDs, with memoization.", "scope": "", "scopeKind": ""}], "calls": ["React", "useMemo", "recipes.filter", "favorites.includes", "favRecipes.map", "RecipeCard", "openRecipe", "toggleFavorite"], "search-terms": ["Favorites", "favorite recipes", "React component", "useMemo", "RecipeCard", "favorites list", "frontend React"], "state": 2, "file_id": 21, "knowledge_revision": 43, "git_revision": "", "ctags": [{"_type": "tag", "name": "Favorites", "path": "/home/kavia/workspace/code-generation/recipe-explorer-15926-15935/frontend_recipe_app/src/pages/Favorites.jsx", "pattern": "/^export default function Favorites({ recipes, favorites, openRecipe, toggleFavorite }) {$/", "language": "JavaScript", "kind": "function", "signature": "({ recipes, favorites, openRecipe, toggleFavorite })"}], "hash": "afe09f87b90a91135c44c9d9d5619c30", "format-version": 4, "code-base-name": "frontend_recipe_app", "filename": "frontend_recipe_app/src/pages/Favorites.jsx", "revision_history": [{"43": ""}]}