{"is_source_file": true, "format": "JavaScript (React/JSX)", "description": "The file is the main React application component 'App.js' that manages routing, authentication, favorite recipes, and page rendering for a recipe explorer web application.", "external_files": ["./styles/global.css", "./data/mockData", "./components/Header", "./pages/Recipes", "./pages/Favorites", "./pages/RecipeDetails", "./pages/Profile", "./pages/SignIn", "./utils/storage"], "external_methods": ["getFavorites", "setFavorites", "getUser", "setUser", "clearUser"], "published": ["App"], "classes": [], "methods": [{"name": "App()", "description": "Main React functional component managing navigation, user state, recipes, favorites, and routing logic.", "scope": "", "scopeKind": ""}], "calls": ["setFavorites", "getFavorites", "getUser", "setUser", "clearUser", "useEffect", "useState", "useMemo", "setRoute", "setSelectedId", "setCurrentUser", "window.scrollTo"], "search-terms": ["React main app component", "recipe explorer", "user authentication", "favorites management", "routing logic", "state management", "UI navigation", "recipe data", "page rendering"], "state": 2, "file_id": 6, "knowledge_revision": 50, "git_revision": "939a6acb7bbe88f789805a144097c130ddd5311a", "revision_history": [{"24": "939a6acb7bbe88f789805a144097c130ddd5311a"}, {"50": "939a6acb7bbe88f789805a144097c130ddd5311a"}], "ctags": [{"_type": "tag", "name": "App", "path": "/home/kavia/workspace/code-generation/recipe-explorer-15926-15935/frontend_recipe_app/src/App.js", "pattern": "/^function App() {$/", "language": "JavaScript", "kind": "function", "signature": "()"}, {"_type": "tag", "name": "avatar", "path": "/home/kavia/workspace/code-generation/recipe-explorer-15926-15935/frontend_recipe_app/src/App.js", "pattern": "/^      avatar: userPartial.avatar || defaultUser.avatar,$/", "language": "JavaScript", "kind": "property", "scope": "App.user", "scopeKind": "class"}, {"_type": "tag", "name": "email", "path": "/home/kavia/workspace/code-generation/recipe-explorer-15926-15935/frontend_recipe_app/src/App.js", "pattern": "/^      email: userPartial.email || defaultUser.email,$/", "language": "JavaScript", "kind": "property", "scope": "App.user", "scopeKind": "class"}, {"_type": "tag", "name": "favorites", "path": "/home/kavia/workspace/code-generation/recipe-explorer-15926-15935/frontend_recipe_app/src/App.js", "pattern": "/^      favorites: favorites,$/", "language": "JavaScript", "kind": "property", "scope": "App.user", "scopeKind": "class"}, {"_type": "tag", "name": "id", "path": "/home/kavia/workspace/code-generation/recipe-explorer-15926-15935/frontend_recipe_app/src/App.js", "pattern": "/^      id: \"local\",$/", "language": "JavaScript", "kind": "property", "scope": "App.user", "scopeKind": "class"}, {"_type": "tag", "name": "name", "path": "/home/kavia/workspace/code-generation/recipe-explorer-15926-15935/frontend_recipe_app/src/App.js", "pattern": "/^      name: userPartial.name || defaultUser.name,$/", "language": "JavaScript", "kind": "property", "scope": "App.user", "scopeKind": "class"}, {"_type": "tag", "name": "user", "path": "/home/kavia/workspace/code-generation/recipe-explorer-15926-15935/frontend_recipe_app/src/App.js", "pattern": "/^    const user = {$/", "language": "JavaScript", "kind": "class", "scope": "App", "scopeKind": "class"}], "hash": "4cae04c31676fa8eb09ecf9eab57bc12", "format-version": 4, "code-base-name": "frontend_recipe_app", "filename": "frontend_recipe_app/src/App.js", "fields": [{"name": "avatar: userPartial.avatar || defaultUser.avatar,", "scope": "App.user", "scopeKind": "class", "description": "unavailable"}, {"name": "email: userPartial.email || defaultUser.email,", "scope": "App.user", "scopeKind": "class", "description": "unavailable"}, {"name": "favorites: favorites,", "scope": "App.user", "scopeKind": "class", "description": "unavailable"}, {"name": "id: \"local\",", "scope": "App.user", "scopeKind": "class", "description": "unavailable"}, {"name": "name: userPartial.name || defaultUser.name,", "scope": "App.user", "scopeKind": "class", "description": "unavailable"}]}